[
    {
        "Title": "Turing goes Flutter",
        "Lang": "IT",
        "Description": "Unisciti a noi ad un evento dedicato a Flutter, per provare le ultime novità dell’SDK gratuito e open source di Google. Scoprirai come utilizzarlo per la creazione di app native iOS e Android da un singolo codice sorgente.",
        "Datetime": "2019 12 04",
        "Image Link": "https://hknpolito.org/wp-content/uploads/2018/11/46420860_1131453843696636_421282716315549696_o-1024x576.jpg",
        "Facebook Link": "https://www.facebook.com/events/522962258113618/",
        "Eventbrite Link": null
    },
    {
        "Title": "Like@Home",
        "Lang": "EN",
        "Description": "Unisciti a noi ad un evento dedicato a Flutter, per provare le ultime novità dell’SDK gratuito e open source di Google. Scoprirai come utilizzarlo per la creazione di app native iOS e Android da un singolo codice sorgente.",
        "Datetime": "2019 12 04",
        "Image Link": "https://hknpolito.org/wp-content/uploads/2018/11/46420860_1131453843696636_421282716315549696_o-1024x576.jpg",
        "Facebook Link": "https://www.facebook.com/events/522962258113618/",
        "Eventbrite Link": null
    }
]
